pypinetworktest_ttataryn26/__init__.py
pypinetworktest_ttataryn26/feedParse.py
pypinetworktest_ttataryn26/test.py
pypinetworktest_ttataryn26-0.4.dist-info/METADATA
pypinetworktest_ttataryn26-0.4.dist-info/WHEEL
pypinetworktest_ttataryn26-0.4.dist-info/top_level.txt
pypinetworktest_ttataryn26-0.4.dist-info/RECORD
