Metadata-Version: 2.1
Name: pypinetworktest-ttataryn26
Version: 0.4
Summary: test pypi network traffic
Author-email: Example author <Author@example.com>
